{"impl": {"impl_id": "verus-real-prophecy-988105e1bb46-fail-conditional_expression_propagate1-31", "spec_id": "verus-real-prophecy-988105e1bb46", "status": "fail", "whole_impl_energy": -4.698883533477783, "spec_text": "\n        #[verifier::prophetic] uninterp spec fn proph() -> bool;\n        #[verifier::prophetic] uninterp spec fn proph_int() -> int;\n\n        spec fn test(b: bool, x: int, y: int) -> int {\n            if b { proph_int() } else { x }\n        }\n    ", "impl_text": "\n        #[verifier::prophetic] uninterp spec fn proph() -> bool;\n        #[verifier::prophetic] uninterp spec fn proph_int() -> int;\n\n        spec fn test(b: bool, x: int, y: int) -> int {\n            if b { proph_int() } else { x }\n        }\n    "}, "lines": [{"line_idx": 0, "line_text": "        #[verifier::prophetic] uninterp spec fn proph() -> bool;", "energy": -4.70166540145874, "is_buggy": false, "x": 0.25478559732437134, "y": -3.6628618240356445}, {"line_idx": 1, "line_text": "        #[verifier::prophetic] uninterp spec fn proph_int() -> int;", "energy": -4.712323188781738, "is_buggy": false, "x": -0.5262346267700195, "y": -2.596315622329712}, {"line_idx": 2, "line_text": "        spec fn test(b: bool, x: int, y: int) -> int {", "energy": -4.576666355133057, "is_buggy": false, "x": -6.065154075622559, "y": -0.198228120803833}, {"line_idx": 3, "line_text": "            if b { proph_int() } else { x }", "energy": -4.06144380569458, "is_buggy": false, "x": -3.3042094707489014, "y": -2.9097373485565186}, {"line_idx": 4, "line_text": "        }", "energy": -4.937946796417236, "is_buggy": false, "x": -0.733022928237915, "y": 13.079185485839844}]}