{"impl": {"impl_id": "verus-real-recursion-512fa5c6158b-fail-decreases_in_pure_exp-54", "spec_id": "verus-real-recursion-512fa5c6158b", "status": "fail", "whole_impl_energy": 0.47759810090065, "spec_text": "\n        spec fn f(n: int) -> bool\n            decreases n\n        {\n            (|b: bool| b)(f(n)) // FAILS\n        }\n    ", "impl_text": "\n        spec fn f(n: int) -> bool\n            decreases n\n        {\n            (|b: bool| b)(f(n)) // FAILS\n        }\n    "}, "lines": [{"line_idx": 0, "line_text": "        spec fn f(n: int) -> bool", "energy": -5.3626227378845215, "is_buggy": false, "x": -0.05102306604385376, "y": -3.361450433731079}, {"line_idx": 1, "line_text": "            decreases n", "energy": -5.829222679138184, "is_buggy": false, "x": 0.6645110845565796, "y": -1.9557154178619385}, {"line_idx": 2, "line_text": "        {", "energy": -5.646482944488525, "is_buggy": false, "x": -8.156482696533203, "y": 3.245306968688965}, {"line_idx": 3, "line_text": "            (|b: bool| b)(f(n)) // FAILS", "energy": -5.581790447235107, "is_buggy": true, "x": 8.194694519042969, "y": -3.2641568183898926}, {"line_idx": 4, "line_text": "        }", "energy": -5.1464152336120605, "is_buggy": false, "x": -0.025844335556030273, "y": 13.607425689697266}]}