{"impl": {"impl_id": "verus-real-fndef_types-4e5923a5eb0b-fail-recursion11_via_fn_mut-14", "spec_id": "verus-real-fndef_types-4e5923a5eb0b", "status": "fail", "whole_impl_energy": -1.6391382217407227, "spec_text": "\n        spec fn foo<F: FnMut(u8)>(f: F) -> bool {\n            call_requires(f, (0,))\n        }\n\n        fn test(x: u8)\n            requires foo(test)\n        {\n        }\n    ", "impl_text": "\n        spec fn foo<F: FnMut(u8)>(f: F) -> bool {\n            call_requires(f, (0,))\n        }\n\n        fn test(x: u8)\n            requires foo(test)\n        {\n        }\n    "}, "lines": [{"line_idx": 0, "line_text": "        spec fn foo<F: FnMut(u8)>(f: F) -> bool {", "energy": -3.949063539505005, "is_buggy": false, "x": -7.02676248550415, "y": -2.1098079681396484}, {"line_idx": 1, "line_text": "            call_requires(f, (0,))", "energy": -3.4712586402893066, "is_buggy": false, "x": 4.665261745452881, "y": 1.269334316253662}, {"line_idx": 2, "line_text": "        }", "energy": -4.71828031539917, "is_buggy": false, "x": -1.1622711420059204, "y": 12.611055374145508}, {"line_idx": 3, "line_text": "        fn test(x: u8)", "energy": -5.307904243469238, "is_buggy": false, "x": -1.8126024007797241, "y": -2.293063163757324}, {"line_idx": 4, "line_text": "            requires foo(test)", "energy": -4.659730911254883, "is_buggy": false, "x": -1.6714807748794556, "y": -2.385484218597412}, {"line_idx": 5, "line_text": "        {", "energy": -5.254735469818115, "is_buggy": false, "x": -7.954769611358643, "y": 3.26550030708313}, {"line_idx": 6, "line_text": "        }", "energy": -4.637985706329346, "is_buggy": false, "x": -0.609400749206543, "y": 12.889650344848633}]}