{"impl": {"impl_id": "verus-real-recursion-b254c843ffb9-fail-basic_decreases_by_int_fail9-26", "spec_id": "verus-real-recursion-b254c843ffb9", "status": "fail", "whole_impl_energy": -3.895454168319702, "spec_text": "\n        spec fn arith_sum<A, B>(a: A, b: B, i: int) -> int\n            decreases i\n        {\n            decreases_when(i >= 0);\n            decreases_by(check_arith_sum::<int, int>);\n\n            if i == 0 { 0 } else { i + arith_sum(a, b, i - 1) }\n        }\n\n        #[verifier(decreases_by)]\n        proof fn check_arith_sum<B, A>(a: A, b: B, i: int) {\n        }\n    ", "impl_text": "\n        spec fn arith_sum<A, B>(a: A, b: B, i: int) -> int\n            decreases i\n        {\n            decreases_when(i >= 0);\n            decreases_by(check_arith_sum::<int, int>);\n\n            if i == 0 { 0 } else { i + arith_sum(a, b, i - 1) }\n        }\n\n        #[verifier(decreases_by)]\n        proof fn check_arith_sum<B, A>(a: A, b: B, i: int) {\n        }\n    "}, "lines": [{"line_idx": 0, "line_text": "        spec fn arith_sum<A, B>(a: A, b: B, i: int) -> int", "energy": -4.48125696182251, "is_buggy": false, "x": 0.009931161999702454, "y": -3.634718656539917}, {"line_idx": 1, "line_text": "            decreases i", "energy": -5.544450759887695, "is_buggy": false, "x": 0.708280622959137, "y": -1.996036410331726}, {"line_idx": 2, "line_text": "        {", "energy": -5.288015842437744, "is_buggy": false, "x": -8.233009338378906, "y": 3.207430839538574}, {"line_idx": 3, "line_text": "            decreases_when(i >= 0);", "energy": -4.289371013641357, "is_buggy": false, "x": -3.6984612941741943, "y": -1.852588415145874}, {"line_idx": 4, "line_text": "            decreases_by(check_arith_sum::<int, int>);", "energy": -2.964165449142456, "is_buggy": false, "x": 5.263339042663574, "y": 2.5823071002960205}, {"line_idx": 5, "line_text": "            if i == 0 { 0 } else { i + arith_sum(a, b, i - 1) }", "energy": -3.783512592315674, "is_buggy": false, "x": 2.453903913497925, "y": 1.5461915731430054}, {"line_idx": 6, "line_text": "        }", "energy": -4.563390254974365, "is_buggy": false, "x": 0.1832282543182373, "y": 14.121307373046875}, {"line_idx": 7, "line_text": "        #[verifier(decreases_by)]", "energy": -4.372002601623535, "is_buggy": false, "x": -1.4088129997253418, "y": -5.445616722106934}, {"line_idx": 8, "line_text": "        proof fn check_arith_sum<B, A>(a: A, b: B, i: int) {", "energy": -3.4068477153778076, "is_buggy": false, "x": -3.14467716217041, "y": 1.7010822296142578}, {"line_idx": 9, "line_text": "        }", "energy": -3.923489809036255, "is_buggy": false, "x": 0.4310314655303955, "y": 12.443309783935547}]}