{"impl": {"impl_id": "verus-real-control_flow-da39a3ee5e6b-fail-conditionals_units_return_fail-9", "spec_id": "verus-real-control_flow-da39a3ee5e6b", "status": "fail", "whole_impl_energy": 0.39936843514442444, "spec_text": "", "impl_text": "        fn if_unit_no_else() {\n            let x = if true { () };\n            assert(false); // FAILS\n        }\n\n        fn if_let(b: bool) {\n            let r = if b { let mut x = 5; x = 7; x } else { return; };\n            assert(r == 5); // FAILS\n        }\n    "}, "lines": [{"line_idx": 0, "line_text": "        fn if_unit_no_else() {", "energy": -4.109434604644775, "is_buggy": false, "x": -9.444392204284668, "y": -3.5373241901397705}, {"line_idx": 1, "line_text": "            let x = if true { () };", "energy": -3.448018789291382, "is_buggy": false, "x": 4.681968688964844, "y": 0.5637592077255249}, {"line_idx": 2, "line_text": "            assert(false); // FAILS", "energy": -4.315496921539307, "is_buggy": true, "x": 9.374155044555664, "y": -2.555572032928467}, {"line_idx": 3, "line_text": "        }", "energy": -4.933394432067871, "is_buggy": false, "x": -0.1889643669128418, "y": 11.656377792358398}, {"line_idx": 4, "line_text": "        fn if_let(b: bool) {", "energy": -4.747843265533447, "is_buggy": false, "x": -5.568451404571533, "y": 2.4357781410217285}, {"line_idx": 5, "line_text": "            let r = if b { let mut x = 5; x = 7; x } else { return; };", "energy": -3.349816083908081, "is_buggy": false, "x": 4.6991424560546875, "y": 1.5500569343566895}, {"line_idx": 6, "line_text": "            assert(r == 5); // FAILS", "energy": -3.9608705043792725, "is_buggy": true, "x": 9.15910816192627, "y": -2.3008596897125244}, {"line_idx": 7, "line_text": "        }", "energy": -4.979173183441162, "is_buggy": false, "x": 1.009692668914795, "y": 12.445697784423828}]}