{"impl": {"impl_id": "verus-real-traits-b7af40c4ab3a-fail-impl_of_non_private_trait_fn_must_be_open_or_closed_1_regression_382-97", "spec_id": "verus-real-traits-b7af40c4ab3a", "status": "fail", "whole_impl_energy": -3.4810240268707275, "spec_text": "\n        mod m1 {\n            pub trait SomeTrait {\n                spec fn foo(&self) -> bool;\n            }\n\n            struct SomeType { b: bool }\n\n            impl SomeTrait for SomeType {\n                spec fn foo(&self) -> bool {\n                    self.b\n                }\n            }\n        }\n    ", "impl_text": "\n        mod m1 {\n            pub trait SomeTrait {\n                spec fn foo(&self) -> bool;\n            }\n\n            struct SomeType { b: bool }\n\n            impl SomeTrait for SomeType {\n                spec fn foo(&self) -> bool {\n                    self.b\n                }\n            }\n        }\n    "}, "lines": [{"line_idx": 0, "line_text": "        mod m1 {", "energy": -4.801501750946045, "is_buggy": false, "x": -7.447509765625, "y": -1.523005485534668}, {"line_idx": 1, "line_text": "            pub trait SomeTrait {", "energy": -5.013487815856934, "is_buggy": false, "x": -6.238302230834961, "y": 0.037055134773254395}, {"line_idx": 2, "line_text": "                spec fn foo(&self) -> bool;", "energy": -5.231385231018066, "is_buggy": false, "x": -0.9019903540611267, "y": -1.8125618696212769}, {"line_idx": 3, "line_text": "            }", "energy": -5.074615955352783, "is_buggy": false, "x": -1.2065246105194092, "y": 13.194070816040039}, {"line_idx": 4, "line_text": "            struct SomeType { b: bool }", "energy": -4.348420143127441, "is_buggy": false, "x": -2.5797805786132812, "y": -2.1374917030334473}, {"line_idx": 5, "line_text": "            impl SomeTrait for SomeType {", "energy": -4.731560230255127, "is_buggy": false, "x": -5.739169120788574, "y": 0.9270025491714478}, {"line_idx": 6, "line_text": "                spec fn foo(&self) -> bool {", "energy": -4.868489742279053, "is_buggy": false, "x": -5.798210144042969, "y": 1.2260043621063232}, {"line_idx": 7, "line_text": "                    self.b", "energy": -5.094105243682861, "is_buggy": false, "x": -0.6023756265640259, "y": -0.601202666759491}, {"line_idx": 8, "line_text": "                }", "energy": -4.991413116455078, "is_buggy": false, "x": 0.9637147188186646, "y": 14.573226928710938}, {"line_idx": 9, "line_text": "            }", "energy": -4.939197540283203, "is_buggy": false, "x": 0.18662619590759277, "y": 13.503145217895508}, {"line_idx": 10, "line_text": "        }", "energy": -5.105869770050049, "is_buggy": false, "x": 0.264113187789917, "y": 13.544323921203613}]}