{"impl": {"impl_id": "verus-real-external_fn_specification-68fe152dda96-fail-external_trait_impl_item_error-60", "spec_id": "verus-real-external_fn_specification-68fe152dda96", "status": "fail", "whole_impl_energy": -3.044217824935913, "spec_text": "\n        trait Tr {\n            fn foo(&self);\n        }\n\n        pub struct X { t: u8 }\n\n        impl Tr for X {\n            #[verifier::external]", "impl_text": "            fn foo(&self) { }\n        }\n    "}, "lines": [{"line_idx": 0, "line_text": "            fn foo(&self) { }", "energy": -3.215916156768799, "is_buggy": false, "x": -4.046261787414551, "y": -3.5647621154785156}, {"line_idx": 1, "line_text": "        }", "energy": -4.3776021003723145, "is_buggy": false, "x": -1.55870521068573, "y": 11.018213272094727}]}