{"impl": {"impl_id": "verus-real-recommends-e4c565d40d7c-fail-ensures_forall_recommends_failure-0", "spec_id": "verus-real-recommends-e4c565d40d7c", "status": "fail", "whole_impl_energy": 2.3857991695404053, "spec_text": "\n        spec fn foo(i: int) -> bool\n          recommends 0 <= i < 5,\n        {\n          i + 3 == 20\n        }\n\n        proof fn some_proof()\n            ensures forall |i: int| 0 <= i < 20 ==> foo(i),  // FAILS\n        {\n        }\n    ", "impl_text": "\n        spec fn foo(i: int) -> bool\n          recommends 0 <= i < 5,\n        {\n          i + 3 == 20\n        }\n\n        proof fn some_proof()\n            ensures forall |i: int| 0 <= i < 20 ==> foo(i),  // FAILS\n        {\n        }\n    "}, "lines": [{"line_idx": 0, "line_text": "        spec fn foo(i: int) -> bool", "energy": -4.741016864776611, "is_buggy": false, "x": -0.005520343780517578, "y": -3.4484989643096924}, {"line_idx": 1, "line_text": "          recommends 0 <= i < 5,", "energy": -4.864776134490967, "is_buggy": false, "x": 0.11554521322250366, "y": -2.205805778503418}, {"line_idx": 2, "line_text": "        {", "energy": -5.29965353012085, "is_buggy": false, "x": -8.201010704040527, "y": 3.2419090270996094}, {"line_idx": 3, "line_text": "          i + 3 == 20", "energy": -4.8775715827941895, "is_buggy": false, "x": 1.0403565168380737, "y": -1.1149530410766602}, {"line_idx": 4, "line_text": "        }", "energy": -4.9981536865234375, "is_buggy": false, "x": -0.19783425331115723, "y": 13.761251449584961}, {"line_idx": 5, "line_text": "        proof fn some_proof()", "energy": -4.52286958694458, "is_buggy": false, "x": -0.09033378958702087, "y": -1.720895767211914}, {"line_idx": 6, "line_text": "            ensures forall |i: int| 0 <= i < 20 ==> foo(i),  // FAILS", "energy": -4.669633388519287, "is_buggy": true, "x": 8.844644546508789, "y": -2.9670801162719727}, {"line_idx": 7, "line_text": "        {", "energy": -4.980490207672119, "is_buggy": false, "x": -7.505764007568359, "y": 3.6655707359313965}, {"line_idx": 8, "line_text": "        }", "energy": -4.04571008682251, "is_buggy": false, "x": 0.453763484954834, "y": 12.78746509552002}]}