{"impl": {"impl_id": "verus-real-unions-267c5d41c42c-fail-get_union_field_non_union-2", "spec_id": "verus-real-unions-267c5d41c42c", "status": "fail", "whole_impl_energy": -4.920130252838135, "spec_text": "\n        enum X {\n            Foo(u8),\n            Stuff(bool),\n        }\n", "impl_text": "        fn test_fail(x: X) {\n            assert(get_union_field::<_, u8>(x, \"Foo\") == 5);\n        }\n    "}, "lines": [{"line_idx": 0, "line_text": "        fn test_fail(x: X) {", "energy": -4.158353328704834, "is_buggy": false, "x": -9.05692195892334, "y": -3.374030590057373}, {"line_idx": 1, "line_text": "            assert(get_union_field::<_, u8>(x, \"Foo\") == 5);", "energy": -2.5774147510528564, "is_buggy": false, "x": 5.425485610961914, "y": 2.300004243850708}, {"line_idx": 2, "line_text": "        }", "energy": -4.107237339019775, "is_buggy": false, "x": -0.9915802478790283, "y": 10.921918869018555}]}