{"impl": {"impl_id": "verus-real-prophecy-a6ab1cf8cc99-fail-decreases_clause_exec_fn_cannot_be_prophetic-1", "spec_id": "verus-real-prophecy-a6ab1cf8cc99", "status": "fail", "whole_impl_energy": -5.285684585571289, "spec_text": "\n        #[verifier::prophetic]\n        uninterp spec fn foo() -> int;\n\n        fn test()\n            decreases foo()\n        {\n            test();\n        }\n    ", "impl_text": "\n        #[verifier::prophetic]\n        uninterp spec fn foo() -> int;\n\n        fn test()\n            decreases foo()\n        {\n            test();\n        }\n    "}, "lines": [{"line_idx": 0, "line_text": "        #[verifier::prophetic]", "energy": -4.277217388153076, "is_buggy": false, "x": -0.32474786043167114, "y": -5.639017581939697}, {"line_idx": 1, "line_text": "        uninterp spec fn foo() -> int;", "energy": -4.873804569244385, "is_buggy": false, "x": -0.09797018766403198, "y": -2.553833246231079}, {"line_idx": 2, "line_text": "        fn test()", "energy": -5.583808422088623, "is_buggy": false, "x": 0.3708224892616272, "y": -2.055974245071411}, {"line_idx": 3, "line_text": "            decreases foo()", "energy": -5.287647724151611, "is_buggy": false, "x": 0.7260578870773315, "y": -1.6624149084091187}, {"line_idx": 4, "line_text": "        {", "energy": -5.382497310638428, "is_buggy": false, "x": -7.955375671386719, "y": 3.3040225505828857}, {"line_idx": 5, "line_text": "            test();", "energy": -5.004824161529541, "is_buggy": false, "x": 0.18399876356124878, "y": -0.9642417430877686}, {"line_idx": 6, "line_text": "        }", "energy": -4.683724880218506, "is_buggy": false, "x": -0.3800077438354492, "y": 13.24195671081543}]}