{"impl": {"impl_id": "verus-real-traits-db0a245878f5-fail-disallow_external_body_drop_with_requires-93", "spec_id": "verus-real-traits-db0a245878f5", "status": "fail", "whole_impl_energy": -5.267373561859131, "spec_text": "\n        struct A { v: u64 }\n\n        impl Drop for A {\n            #[verifier::external_body]\n            fn drop(&mut self)\n                requires false\n            {\n            }\n        }\n    ", "impl_text": "\n        struct A { v: u64 }\n\n        impl Drop for A {\n            #[verifier::external_body]\n            fn drop(&mut self)\n                requires false\n            {\n            }\n        }\n    "}, "lines": [{"line_idx": 0, "line_text": "        struct A { v: u64 }", "energy": -4.272687911987305, "is_buggy": false, "x": -3.1154842376708984, "y": -3.2250776290893555}, {"line_idx": 1, "line_text": "        impl Drop for A {", "energy": -4.671505451202393, "is_buggy": false, "x": -6.203709602355957, "y": -0.32291877269744873}, {"line_idx": 2, "line_text": "            #[verifier::external_body]", "energy": -4.994682312011719, "is_buggy": false, "x": -0.8594359755516052, "y": -5.297233581542969}, {"line_idx": 3, "line_text": "            fn drop(&mut self)", "energy": -5.0944743156433105, "is_buggy": false, "x": -1.412209153175354, "y": -2.116013765335083}, {"line_idx": 4, "line_text": "                requires false", "energy": -5.306757926940918, "is_buggy": false, "x": 0.04079285264015198, "y": -1.2520442008972168}, {"line_idx": 5, "line_text": "            {", "energy": -5.0886454582214355, "is_buggy": false, "x": -7.624988555908203, "y": 3.511547327041626}, {"line_idx": 6, "line_text": "            }", "energy": -4.435314178466797, "is_buggy": false, "x": -0.2544522285461426, "y": 13.157094955444336}, {"line_idx": 7, "line_text": "        }", "energy": -4.877858638763428, "is_buggy": false, "x": -0.14856863021850586, "y": 13.390625}]}